{
  "atualizado": "2026-07-18T11:05:08+00:00",
  "itens": [
    {
      "titulo": "Relógio para treino: 10 smartwatches para esportes e academia",
      "link": "https://tecnoblog.net/guias/relogio-para-treino-e-esportes/",
      "fonte": "Tecnoblog",
      "data": "2026-07-17"
    },
    {
      "titulo": "5 perguntas que Silo precisa responder na temporada 3",
      "link": "https://canaltech.com.br/entretenimento/silo-perguntas-que-precisam-resposta/",
      "fonte": "Canaltech",
      "data": "2026-07-18"
    },
    {
      "titulo": "Após 4 mil anos, é reveledo o segredo das princesas do Egito Antigo",
      "link": "https://olhardigital.com.br/2026/07/18/ciencia-e-espaco/apos-4-mil-anos-e-reveledo-o-segredo-das-princesas-do-egito-antigo/",
      "fonte": "Olhar Digital",
      "data": "2026-07-18"
    },
    {
      "titulo": "iPhone com melhor custo-benefício em 2026: qual celular da Apple comprar?",
      "link": "https://tecnoblog.net/guias/melhor-iphone-custo-beneficio/",
      "fonte": "Tecnoblog",
      "data": "2026-07-17"
    },
    {
      "titulo": "Quais carros híbridos ainda serão lançados no Brasil em 2026?",
      "link": "https://canaltech.com.br/carros/quais-carros-hibridos-ainda-serao-lancados-no-brasil-em-2026/",
      "fonte": "Canaltech",
      "data": "2026-07-17"
    },
    {
      "titulo": "Oceano profundo da Antártida muda de ritmo e ameaça equilíbrio do planeta",
      "link": "https://olhardigital.com.br/2026/07/18/ciencia-e-espaco/oceano-profundo-da-antartida-muda-de-ritmo-e-ameaca-equilibrio-do-planeta/",
      "fonte": "Olhar Digital",
      "data": "2026-07-18"
    },
    {
      "titulo": "Motorola Signature tem cupom de R$ 3.000 em oferta parcelável até 10x",
      "link": "https://tecnoblog.net/achados/motorola-signature-tem-cupom-de-r-3-000-em-oferta-parcelavel-ate-10x/",
      "fonte": "Tecnoblog",
      "data": "2026-07-17"
    },
    {
      "titulo": "GWM faz loucura para limpar estoques de SUV de luxo, mas por tempo limitado",
      "link": "https://canaltech.com.br/carros/gwm-faz-loucura-para-limpar-estoques-de-suv-de-luxo-por-tempo-limitado/",
      "fonte": "Canaltech",
      "data": "2026-07-17"
    },
    {
      "titulo": "França x Inglaterra: onde assistir, horário e escalações do jogo da Copa do Mundo",
      "link": "https://olhardigital.com.br/2026/07/18/internet-e-redes-sociais/franca-x-inglaterra-onde-assistir-horario-e-escalacoes-do-jogo-da-copa-do-mundo/",
      "fonte": "Olhar Digital",
      "data": "2026-07-18"
    },
    {
      "titulo": "Custo-benefício: Galaxy Tab S10 FE tem 39% OFF em oferta até 12x sem juros",
      "link": "https://tecnoblog.net/achados/custo-beneficio-galaxy-tab-s10-fe-tem-39-off-em-oferta-ate-12x-sem-juros/",
      "fonte": "Tecnoblog",
      "data": "2026-07-17"
    },
    {
      "titulo": "Google é forçado a compartilhar dados com rivais de IA; entenda o motivo",
      "link": "https://canaltech.com.br/mercado/google-e-forcado-a-compartilhar-dados-com-rivais-de-ia-entenda-o-motivo/",
      "fonte": "Canaltech",
      "data": "2026-07-17"
    },
    {
      "titulo": "Brasil é o 3º país mais atacado por ransomware; especialistas explicam o motivo",
      "link": "https://olhardigital.com.br/2026/07/17/seguranca/brasil-e-o-3-pais-mais-atacado-por-ransomware-especialistas-explicam-o-motivo/",
      "fonte": "Olhar Digital",
      "data": "2026-07-18"
    },
    {
      "titulo": "Evoto AI usa IA para agilizar edição profissional de imagens",
      "link": "https://tecnoblog.net/publieditoriais/evoto-ai-usa-ia-para-agilizar-edicao-profissional-de-imagens/",
      "fonte": "Tecnoblog",
      "data": "2026-07-17"
    },
    {
      "titulo": "Rádio 3.0 já chegou a 7 cidades brasileiras; veja se a sua está na lista",
      "link": "https://canaltech.com.br/telecom/radio-3-0-ja-chegou-a-7-cidades-brasileiras-veja-se-a-sua-esta-na-lista/",
      "fonte": "Canaltech",
      "data": "2026-07-17"
    },
    {
      "titulo": "Casa Branca passa a controlar acesso a modelos de IA de ponta",
      "link": "https://olhardigital.com.br/2026/07/17/pro/casa-branca-passa-a-controlar-acesso-a-modelos-de-ia-de-ponta/",
      "fonte": "Olhar Digital",
      "data": "2026-07-18"
    },
    {
      "titulo": "Motorola Razr Fold (1 TB) é caro, mas tem cupom generoso nesta oferta",
      "link": "https://tecnoblog.net/achados/motorola-razr-fold-1-tb-e-caro-mas-tem-cupom-generoso-nesta-oferta/",
      "fonte": "Tecnoblog",
      "data": "2026-07-17"
    },
    {
      "titulo": "Capinha muito grossa estraga bateria do iPhone? Veja o que diz a Apple",
      "link": "https://canaltech.com.br/smartphone/capinha-muito-grossa-estraga-bateria-do-i-phone-veja-o-que-diz-a-apple/",
      "fonte": "Canaltech",
      "data": "2026-07-17"
    },
    {
      "titulo": "Açúcar encontrado no espaço pode mudar tudo o que sabemos sobre a origem da vida",
      "link": "https://olhardigital.com.br/2026/07/17/ciencia-e-espaco/acucar-encontrado-no-espaco-pode-mudar-tudo-o-que-sabemos-sobre-a-origem-da-vida/",
      "fonte": "Olhar Digital",
      "data": "2026-07-18"
    }
  ]
}